py_context-0.3.1.dist-info/METADATA
py_context-0.3.1.dist-info/RECORD
py_context-0.3.1.dist-info/WHEEL
py_context-0.3.1.dist-info/top_level.txt
pycontext/__init__.py
pycontext/context.py
pycontext/signals.py
