Metadata-Version: 2.1
Name: py-context
Version: 0.3.1
Summary: Python dict with stacked context data
Home-page: https://github.com/dealertrack/py-context
Author: Miroslav Shubernetskiy
Author-email: UNKNOWN
License: MIT
Keywords: context stack
Platform: UNKNOWN
Classifier: Intended Audience :: Developers
Classifier: Natural Language :: English
Classifier: License :: OSI Approved :: MIT License
Classifier: Programming Language :: Python
Classifier: Programming Language :: Python :: 2.7
Classifier: Programming Language :: Python :: 3
Classifier: Development Status :: 2 - Pre-Alpha
Requires-Dist: blinker
Requires-Dist: six
Requires-Dist: setuptools
